psa_car_controller/__init__.py
psa_car_controller/__main__.py
psa_car_controller/common/__init__.py
psa_car_controller/common/mylogger.py
psa_car_controller/common/utils.py
psa_car_controller/psa/AccountInformation.py
psa_car_controller/psa/RemoteClient.py
psa_car_controller/psa/RemoteCredentials.py
psa_car_controller/psa/__init__.py
psa_car_controller/psa/connected_car_api/__init__.py
psa_car_controller/psa/connected_car_api/api/__init__.py
psa_car_controller/psa/connected_car_api/api/trips_api.py
psa_car_controller/psa/connected_car_api/api/user_api.py
psa_car_controller/psa/connected_car_api/api/vehicles_api.py
psa_car_controller/psa/connected_car_api/api_client.py
psa_car_controller/psa/connected_car_api/configuration.py
psa_car_controller/psa/connected_car_api/models/__init__.py
psa_car_controller/psa/connected_car_api/models/adas.py
psa_car_controller/psa/connected_car_api/models/adas_park_assist.py
psa_car_controller/psa/connected_car_api/models/alert.py
psa_car_controller/psa/connected_car_api/models/alert_end_position.py
psa_car_controller/psa/connected_car_api/models/alert_links.py
psa_car_controller/psa/connected_car_api/models/alert_msg_enum.py
psa_car_controller/psa/connected_car_api/models/alerts.py
psa_car_controller/psa/connected_car_api/models/alerts_embedded.py
psa_car_controller/psa/connected_car_api/models/battery.py
psa_car_controller/psa/connected_car_api/models/bounded_program.py
psa_car_controller/psa/connected_car_api/models/charging_status_enum.py
psa_car_controller/psa/connected_car_api/models/circle_zone.py
psa_car_controller/psa/connected_car_api/models/circle_zone_coordinates.py
psa_car_controller/psa/connected_car_api/models/collection_result.py
psa_car_controller/psa/connected_car_api/models/collision.py
psa_car_controller/psa/connected_car_api/models/collision_links.py
psa_car_controller/psa/connected_car_api/models/collision_obj.py
psa_car_controller/psa/connected_car_api/models/collision_obj_front.py
psa_car_controller-3.6.2.dist-info/METADATA
psa_car_controller-3.6.2.dist-info/WHEEL
psa_car_controller-3.6.2.dist-info/entry_points.txt
psa_car_controller-3.6.2.dist-info/licenses/LICENSE
psa_car_controller-3.6.2.dist-info/RECORD
