Metadata-Version: 2.4
Name: psa-car-controller
Version: 3.6.2
Summary: This is a python program to control a psa car with connected_car v4 api.
License: GPL-3.0
License-File: LICENSE
Author: Florian Bezannier
Author-email: florian.bezannier@hotmail.fr
Requires-Python: >=3.11,<4.0.0
Classifier: License :: OSI Approved :: GNU General Public License v3 (GPLv3)
Classifier: Programming Language :: Python :: 3
Classifier: Programming Language :: Python :: 3.11
Classifier: Programming Language :: Python :: 3.12
Classifier: Programming Language :: Python :: 3.13
Classifier: Programming Language :: Python :: 3.14
Requires-Dist: ConfigUpdater (>=3.0)
Requires-Dist: Flask (>=1.0.4)
Requires-Dist: Werkzeug (>=1.0.0)
Requires-Dist: androguard (>=4.1.2,<5.0.0)
Requires-Dist: argparse (>=1.4.0,<2.0.0)
Requires-Dist: certifi (>=14.05.14)
Requires-Dist: cryptography (>=2.6)
Requires-Dist: dash (>=2.9.0,<3.0.0)
Requires-Dist: dash-bootstrap-components (>=1)
Requires-Dist: dash-daq (>=0.5.0,<0.6.0)
Requires-Dist: geojson (>=2.5.0,<3.0.0)
Requires-Dist: importlib-metadata (>=1.7.0) ; python_version < "3.8"
Requires-Dist: ipython (>=7.0.0,<8.0.0)
Requires-Dist: numpy (>=1.24.0,<2.0.0)
Requires-Dist: oauth2-client (>=1.3.0,<2.0.0)
Requires-Dist: paho-mqtt (>=1.5.0,<2.0.0)
Requires-Dist: pandas (>=1.1.5) ; python_version < "3.13"
Requires-Dist: pandas (>=2.3.1,<3.0.0) ; python_version >= "3.13"
Requires-Dist: plotly (>=5)
Requires-Dist: pycryptodomex (==3.23.0)
Requires-Dist: pydantic (>=1.9.0,<2.0.0)
Requires-Dist: python-dateutil (>=2.5.3)
Requires-Dist: pytz (>=2021.0,<2022.0)
Requires-Dist: requests (>=2.27.1,<3.0.0)
Requires-Dist: reverse-geocode (>=1.4.1,<2.0.0)
Requires-Dist: ruamel.yaml (>=0.15.0)
Requires-Dist: scipy (<1.11.0) ; python_version < "3.8"
Requires-Dist: scipy (<1.8.0) ; python_version < "3.8"
Requires-Dist: scipy (>=1.9.2) ; python_version >= "3.11"
Requires-Dist: six (>=1.10)
Requires-Dist: urllib3 (>=1.15.1,<2.0.0)
Project-URL: Homepage, https://github.com/flobz/psa_car_controller
Project-URL: Repository, https://github.com/flobz/psa_car_controller
